{"is_source_file": false, "format": "", "description": "", "external_files": [], "external_methods": [], "published": [], "classes": [], "methods": [], "calls": [], "search-terms": [], "state": 2, "file_id": 10, "knowledge_revision": 36, "git_revision": "6ff4ac3bdee44326026f129f3a645e7a66f4560d", "hash": "e6d79c39f1ad5aca57efe177d38dc4ce", "format-version": 4, "code-base-name": "frontend_notes_app", "filename": "frontend_notes_app/src/global.css", "revision_history": [{"36": "6ff4ac3bdee44326026f129f3a645e7a66f4560d"}]}